abejacli/__init__.py
abejacli/bucket/__init__.py
abejacli/bucket/download_job.py
abejacli/bucket/process_file_job.py
abejacli/bucket/upload_job.py
abejacli/click_custom.py
abejacli/common/__init__.py
abejacli/config/__init__.py
abejacli/configuration/__init__.py
abejacli/configuration/config.py
abejacli/configuration/formatter.py
abejacli/configuration/loader.py
abejacli/datalake/__init__.py
abejacli/datalake/download_job.py
abejacli/datalake/process_file_job.py
abejacli/datalake/upload_job.py
abejacli/dataset/__init__.py
abejacli/dataset/commands.py
abejacli/docker/__init__.py
abejacli/docker/commands/__init__.py
abejacli/docker/commands/run.py
abejacli/docker/container_run.py
abejacli/docker/utils.py
abejacli/dx_template/__init__.py
abejacli/dx_template/commands.py
abejacli/exceptions.py
abejacli/fs_utils.py
abejacli/labs/__init__.py
abejacli/labs/commands.py
abejacli/logger.py
abejacli/model/__init__.py
abejacli/model/docker_handler.py
abejacli/model/local_server_manager.py
abejacli/model/runtime_utils.py
abejacli/registry/__init__.py
abejacli/registry/commands.py
abejacli/run.py
abejacli/secret/__init__.py
abejacli/secret/commands.py
abejacli/secret/integration_service_type.py
abejacli/secret_version/__init__.py
abejacli/secret_version/commands.py
abejacli/session.py
abejacli/startapp/__init__.py
abejacli/startapp/commands.py
abejacli/task/__init__.py
abejacli/template/predict.py-tpl
abejacli/template/requirements-local.txt-tpl
abejacli/template/train.py-tpl
abejacli/training/__init__.py
abejacli/training/client.py
abejacli/training/commands.py
abejacli/training/jobs.py
abejacli/version.py
abejacli-2.2.7.dist-info/LICENSE
abejacli-2.2.7.dist-info/METADATA
abejacli-2.2.7.dist-info/WHEEL
abejacli-2.2.7.dist-info/entry_points.txt
abejacli-2.2.7.dist-info/RECORD
